expire/__init__.py
expire/base_cache.py
expire/cache_setting.py
expire/decorator.py
expire/log.py
expire/memcached_cache.py
expire/memory_cache.py
expire/redis_cache.py
expire/serializer.py
expire-0.0.1.dist-info/DESCRIPTION.rst
expire-0.0.1.dist-info/METADATA
expire-0.0.1.dist-info/RECORD
expire-0.0.1.dist-info/WHEEL
expire-0.0.1.dist-info/metadata.json
expire-0.0.1.dist-info/top_level.txt
