Metadata-Version: 2.0
Name: expire
Version: 0.0.1
Summary: Expire aims to make using cache as convenient as possible.
Home-page: https://github.com/howie6879/expire
Author: Howie Hu
Author-email: xiaozizayang@gmail.com
License: UNKNOWN
Platform: UNKNOWN
Requires-Dist: colorama
Requires-Dist: pymemcache
Requires-Dist: redis
